aiolookin/__init__.py
aiolookin/const.py
aiolookin/error.py
aiolookin/models.py
aiolookin/protocol.py
aiolookin-1.0.0.dist-info/LICENSE
aiolookin-1.0.0.dist-info/METADATA
aiolookin-1.0.0.dist-info/WHEEL
aiolookin-1.0.0.dist-info/top_level.txt
aiolookin-1.0.0.dist-info/RECORD
